xycu/__init__.py
xycu/clients.py
xycu/managers/__init__.py
xycu/managers/nsfw.py
xycu/managers/sfw.py
xycu/models/__init__.py
xycu/models/enums/__init__.py
xycu/models/enums/categories/__init__.py
xycu/models/enums/categories/nsfw.py
xycu/models/enums/categories/sfw.py
xycu/models/images.py
xycu-0.1.1.dist-info/LICENSE
xycu-0.1.1.dist-info/METADATA
xycu-0.1.1.dist-info/WHEEL
xycu-0.1.1.dist-info/RECORD
